eventhandler/__init__.py
eventhandler/management/__init__.py
eventhandler/management/commands/__init__.py
eventhandler/management/commands/event_listener.py
eventhandler/management/commands/list_registered_events.py
django_eventhandler-0.5.5.dist-info/LICENSE.txt
django_eventhandler-0.5.5.dist-info/METADATA
django_eventhandler-0.5.5.dist-info/WHEEL
django_eventhandler-0.5.5.dist-info/top_level.txt
django_eventhandler-0.5.5.dist-info/RECORD
